problemdetails/__init__.py
problemdetails/errors.py
problemdetails/handlers.py
tornado_problem_details-1.1.0.dist-info/METADATA
tornado_problem_details-1.1.0.dist-info/WHEEL
tornado_problem_details-1.1.0.dist-info/licenses/LICENSE.txt
tornado_problem_details-1.1.0.dist-info/RECORD
