Metadata-Version: 2.3
Name: tornado-problem-details
Version: 1.1.0
Summary: RFC-7807 Error Documents for Tornado
Project-URL: Homepage, https://githib.com/dave-shawley/tornado-problem-details
Author-email: Dave Shawley <daveshawley@gmail.com>
License-Expression: BSD-3-Clause
License-File: LICENSE.txt
Classifier: Development Status :: 5 - Production/Stable
Classifier: Environment :: Web Environment
Classifier: Intended Audience :: Developers
Classifier: Programming Language :: Python :: 3.9
Classifier: Programming Language :: Python :: 3.10
Classifier: Programming Language :: Python :: 3.11
Classifier: Programming Language :: Python :: 3.12
Classifier: Topic :: Internet :: WWW/HTTP :: HTTP Servers
Classifier: Topic :: Software Development :: Libraries
Classifier: Typing :: Typed
Requires-Python: >=3.7
Requires-Dist: tornado>=6
